{"transcript":"藞l什inz蓹m什瑟","exists":true,"definitions":["袨锌褌懈褔械褋泻懈械 褝谢械屑械薪褌褘, 懈褋锌芯谢褜蟹褍械屑褘械 写谢褟 褎芯泻褍褋懈褉芯胁泻懈 懈谢懈 褉邪褋褋械懈胁邪薪懈褟 褋胁械褌邪.","效邪褋褌懈 芯褔泻芯胁 懈谢懈 泻芯薪褌邪泻褌薪褘褏 谢懈薪蟹, 泻芯褉褉械泻褌懈褉褍褞褖懈械 蟹褉械薪懈械.","袨斜褗械泻褌懈胁褘 胁 褎芯褌芯邪锌锌邪褉邪褌邪褏 懈谢懈 屑懈泻褉芯褋泻芯锌邪褏."],"examples":["肖芯褌芯谐褉邪褎 褉邪斜芯褌邪谢 褋 褉邪蟹薪褘屑懈 谢懈薪蟹邪屑懈.","袨薪邪 薪芯褋懈褌 芯褔泻懈 褋 褌芯谢褋褌褘屑懈 谢懈薪蟹邪屑懈.","袦懈泻褉芯褋泻芯锌 芯褋薪邪褖械薪 屑芯褖薪褘屑懈 谢懈薪蟹邪屑懈."],"lemma":"谢懈薪蟹邪","lemmaPos":"noun","synonyms":["褋褌褢泻谢邪","芯褔泻懈","芯斜褗械泻褌懈胁褘"],"number":"plural","pluralForm":"谢懈薪蟹褘","gender":"feminine","source":"谢懈薪蟹邪屑懈"}