{"transcript":"za","exists":true,"definitions":["Указывает на местонахождение позади чего-либо","Указывает на направление действия по ту сторону чего-либо","Указывает на цель, предмет стремления или получения","Указывает на причину или основание действия","Указывает на замещение или обмен","Указывает на временной предел или период"],"examples":["стоять за дверью","зайти за угол","бороться за свободу","купить за рубль","сделать за час","пигмент за глазами"],"lemma":"за","lemmaPos":"preposition","synonyms":["позади","взамен","ради","через"],"number":"singular","source":"за"}