{"transcript":"vɫastʲ","exists":true,"definitions":["Право и возможность распоряжаться кем-либо или чем-либо, подчинять своей воле","Политическое господство, государственное управление и его органы","Лица, облеченные правительственными полномочиями"],"examples":["Захват власти","Исполнительная власть","Прийти к власти","Местные власти"],"lemma":"власть","lemmaPos":"noun","synonyms":["господство","правление","могущество","влияние","руководство"],"number":"singular","pluralForm":"власти","gender":"feminine","source":"власть"}