{"source":"Рождественский базар","number":"singular","lemma":"Рождественский базар","lemmaPos":"noun","definitions":["Ежегодная ярмарка, проводимая в преддверии Рождества, где продаются праздничные товары, подарки, еда и напитки.","Традиционное праздничное мероприятие, часто проходящее на открытом воздухе, с киосками, украшениями и развлечениями."],"examples":["Мы посетили Рождественский базар.","На Рождественском базаре было много людей.","Рождественский базар открывается в ноябре."],"synonyms":["Рождественская ярмарка","Новогодний базар"],"transcript":"rɐʐdʲɪˈstvʲenskʲɪj bɐˈzar","gender":"masculine"}